setup.py
piScanner/__init__.py
piScanner/linedr.py
piScanner/mouse.py
piScanner/piScanner.py
piScanner/rect.py
piScanner.egg-info/PKG-INFO
piScanner.egg-info/SOURCES.txt
piScanner.egg-info/dependency_links.txt
piScanner.egg-info/not-zip-safe
piScanner.egg-info/top_level.txt