Metadata-Version: 1.0
Name: piScanner
Version: 0.2
Summary: Scan your images with piScanner
Home-page: https://github.com/hmnhGeek/scanner
Author: hmnhGeek
Author-email: hmnhsharma97@gmail.com
License: MIT
Platform: UNKNOWN
